mawo_razdel/__init__.py
mawo_razdel/record.py
mawo_razdel/rule.py
mawo_razdel/split.py
mawo_razdel/substring.py
mawo_razdel/syntagrus_patterns.py
mawo_razdel/data/corpora_sents.txt.lzma
mawo_razdel/data/corpora_tokens.txt.lzma
mawo_razdel/data/gicrya_sents.txt.lzma
mawo_razdel/data/gicrya_tokens.txt.lzma
mawo_razdel/data/rnc_sents.txt.lzma
mawo_razdel/data/rnc_tokens.txt.lzma
mawo_razdel/data/syntag_sents.txt.lzma
mawo_razdel/data/syntag_tokens.txt.lzma
mawo_razdel/segmenters/__init__.py
mawo_razdel/segmenters/base.py
mawo_razdel/segmenters/punct.py
mawo_razdel/segmenters/sentenize.py
mawo_razdel/segmenters/sokr.py
mawo_razdel/segmenters/tokenize.py
mawo_razdel-1.0.6.dist-info/licenses/LICENSE
mawo_razdel-1.0.6.dist-info/METADATA
mawo_razdel-1.0.6.dist-info/WHEEL
mawo_razdel-1.0.6.dist-info/top_level.txt
mawo_razdel-1.0.6.dist-info/RECORD
